full_adder/adder.vhdl
entity adder is

	-- inputs: `i0` , `i1` , `ci`
	-- outputs: `s` , `co`

	port (i0, i1: in bit; ci : in bit; s : out bit; co : out bit);
end adder;

architecture rtl of adder is
begin
	-- This full-adder architecture contains two current assignments.
	-- Compute the sum
	s <= i0 xor i1 xor ci;
	-- Carry:
	co <= (i0 and i1) or (i0 and ci) or (i1 and ci);
end rtl;

full_adder/adder_tb.vhdl
entity adder_tb is
end adder_tb;

architecture behav of adder_tb is

	-- Declaration of the component that will be instantiated:
	component adder
		port(i0, i1 : in bit; ci : in bit; s : out bit; co : out bit);
	end component;

	for adder_0: adder use entity work.adder;
	signal i0, i1, ci, s, co : bit;

begin
	
	adder_0 : adder port map (i0 => i0 , i1 => i1, ci => ci , s => s , co => co);

	-- now to the real stuff:

	process
		type pattern_type is record
		
		--inputs:
		i0, i1, ci : bit;
		
		--outputs:
		s, co : bit;

		end record;

		-- Patterns (examples) to apply:

		type pattern_array is array (natural range <>) of pattern_type;
		constant patterns: pattern_array :=
		   (('0', '0', '0', '0', '0'),
		   ('0', '0', '1', '1', '0'),
		   ('0', '1', '0', '1', '0'),
		   ('0', '1', '1', '0', '1'),
		   ('1', '0', '0', '1', '0'),
		   ('1', '0', '1', '0', '1'),
		   ('1', '1', '0', '0', '1'),
		   ('1', '1', '1', '1', '1'));

	begin 
		-- execute each example:

		for i in patterns'range loop
		
		--set the inputs:

		i0 <= patterns(i).i0;
		i1 <= patterns(i).i1;
		ci <= patterns(i).ci;

		--wait for the results:

		wait for 1 ns;

		-- check outputs:

		assert s = patterns(i).s
			report "bad sum value" severity error;
		assert co = patterns(i).co
			report "bad carry out value" severity error;
	end loop;
	assert false report "end of test" severity note;

	-- Wait forever to end the simulation:

	wait;
	end process;
end behav;

full_adder/adder.vcd
$date
  Tue Oct 22 23:24:27 2019
$end
$version
  GHDL v0
$end
$timescale
  1 fs
$end
$scope module standard $end
$upscope $end
$scope module adder_tb $end
$var reg 1 ! i0 $end
$var reg 1 " i1 $end
$var reg 1 # ci $end
$var reg 1 $ s $end
$var reg 1 % co $end
$scope module adder_0 $end
$var reg 1 & i0 $end
$var reg 1 ' i1 $end
$var reg 1 ( ci $end
$var reg 1 ) s $end
$var reg 1 * co $end
$upscope $end
$upscope $end
$enddefinitions $end
#0
0!
0"
0#
0$
0%
0&
0'
0(
0)
0*
#1000000
1#
1$
1(
1)
#2000000
1"
0#
1'
0(
#3000000
1#
0$
1%
1(
0)
1*
#4000000
1!
0"
0#
1$
0%
1&
0'
0(
1)
0*
#5000000
1#
0$
1%
1(
0)
1*
#6000000
1"
0#
1'
0(
#7000000
1#
1$
1(
1)
